cachetools_ext/__init__.py
cachetools_ext/fs.py
cachetools_ext/s3.py
cachetools_ext-0.0.8.dist-info/LICENSE.md
cachetools_ext-0.0.8.dist-info/METADATA
cachetools_ext-0.0.8.dist-info/WHEEL
cachetools_ext-0.0.8.dist-info/top_level.txt
cachetools_ext-0.0.8.dist-info/RECORD
