Metadata-Version: 2.1
Name: cachetools-ext
Version: 0.0.8
Home-page: https://github.com/olirice/cachetools_ext
Author: Oliver Rice
License-File: LICENSE.md
Provides-Extra: dev
Requires-Dist: pytest ; extra == 'dev'
Requires-Dist: pytest-cov ; extra == 'dev'
Requires-Dist: moto ; extra == 'dev'
Requires-Dist: pre-commit ; extra == 'dev'
Requires-Dist: pylint ; extra == 'dev'
Requires-Dist: black ; extra == 'dev'
Provides-Extra: s3
Requires-Dist: boto3 ; extra == 's3'
Provides-Extra: test
Requires-Dist: pytest ; extra == 'test'
Requires-Dist: pytest-cov ; extra == 'test'
Requires-Dist: moto ; extra == 'test'
